thunderbird/__init__.py
thunderbird/github.py
thunderbird/mail.py
thunderbird/mail_cmd.py
thunderbird/profiler.py
thunderbird/search.py
thunderbird/tb_webserver.py
thunderbird/version.py
pythunderbird-0.3.2.dist-info/METADATA
pythunderbird-0.3.2.dist-info/WHEEL
pythunderbird-0.3.2.dist-info/entry_points.txt
pythunderbird-0.3.2.dist-info/licenses/LICENSE
pythunderbird-0.3.2.dist-info/RECORD
