Metadata-Version: 2.4
Name: pyThunderbird
Version: 0.3.2
Summary: python based access to Thunderbird mail with nicegui frontend
Project-URL: Home, https://github.com/WolfgangFahl/pyThunderbird
Project-URL: Documentation, http://wiki.bitplan.com/index.php/PyThunderbird
Project-URL: Source, https://github.com/WolfgangFahl/pyThunderbird/blob/master/thunderbird/mail.py
Project-URL: IssueTracker, https://github.com/WolfgangFahl/pyThunderbird/issues
Author-email: Wolfgang Fahl <wf@bitplan.com>
Maintainer-email: Wolfgang Fahl <wf@bitplan.com>
License-Expression: Apache-2.0
License-File: LICENSE
Keywords: mail,nicegui,thunderbird
Classifier: Development Status :: 4 - Beta
Classifier: Environment :: Web Environment
Classifier: Intended Audience :: Developers
Classifier: Intended Audience :: Education
Classifier: Intended Audience :: Science/Research
Classifier: License :: OSI Approved :: Apache Software License
Classifier: Operating System :: OS Independent
Classifier: Programming Language :: Python :: 3 :: Only
Classifier: Programming Language :: Python :: 3.10
Classifier: Programming Language :: Python :: 3.11
Classifier: Programming Language :: Python :: 3.12
Classifier: Programming Language :: Python :: 3.13
Classifier: Topic :: Software Development :: Libraries :: Python Modules
Requires-Python: >=3.10
Requires-Dist: ftfy>=6.1.3
Requires-Dist: ngwidgets>=0.30.3
Requires-Dist: pylodstorage>=0.18.6
Requires-Dist: pyyaml>=6.0
Provides-Extra: test
Requires-Dist: green; extra == 'test'
